[
  {
    "id": 1,
    "img": "assets/watch.png",
    "name": "Watches",
    "price": 240.0,
    "oldPrice": 360.0,
    "description": "Lorem ipsum dolor sit amet, consectetur adipiscing elit. Magna in est adipiscing in phasellus non in justo.",
    "rating": 4.0,
    "code": "Y523201",
    "type": "device",
    "brand": "Apple",
    "category": "Watches",
    "discount": "25% Discount Offer",
    "quantity": 1,
    "isBestSeller": true
  },
  {
    "id": 2,
    "img": "assets/headphone.png",
    "name": "Headphones",
    "price": 600.0,
    "oldPrice": 690.0,
    "description": "Lorem ipsum dolor sit amet, consectetur adipiscing elit. Magna in est adipiscing in phasellus non in justo.",
    "rating": 4.0,
    "code": "Y523201",
    "type": "device",
    "brand": "Apple",
    "category": "Headphones",
    "discount": "5% Cashback Offer",
    "quantity": 1,
    "isBestSeller": false
  },
  {
    "id": 3,
    "img": "assets/laptop.png",
    "name": "Laptop",
    "price": 990.0,
    "oldPrice": 1190.0,
    "description": "Lorem ipsum dolor sit amet, consectetur adipiscing elit. Magna in est adipiscing in phasellus non in justo.",
    "rating": 5.0,
    "code": "Y523201",
    "type": "device",
    "brand": "Apple",
    "category": "Laptop",
    "discount": "5% Cashback Offer",
    "quantity": 1,
    "isBestSeller": true
  },
  {
    "id": 4,
    "img": "assets/blackwatch.png",
    "name": "Black watches",
    "price": 350.0,
    "oldPrice": 590.0,
    "description": "Lorem ipsum dolor sit amet, consectetur adipiscing elit. Magna in est adipiscing in phasellus non in justo.",
    "rating": 4.0,
    "code": "Y523201",
    "type": "device",
    "brand": "Apple",
    "category": "Watches",
    "discount": "25% Discount Offer",
    "quantity": 1,
    "isBestSeller": false
  },
  {
    "id": 5,
    "img": "assets/console.jpeg",
    "name": "Game console",
    "price": 760.0,
    "oldPrice": 860.0,
    "description": "Lorem ipsum dolor sit amet, consectetur adipiscing elit. Magna in est adipiscing in phasellus non in justo.",
    "rating": 5.0,
    "code": "Y523201",
    "type": "device",
    "brand": "Sony",
    "category": "Game Console",
    "discount": "20% Cashback",
    "quantity": 1,
    "isBestSeller": true
  },
  {
    "id": 6,
    "img": "assets/shoe.png",
    "name": "Shoes",
    "price": 270.0,
    "oldPrice": 350.0,
    "description": "Lorem ipsum dolor sit amet, consectetur adipiscing elit. Magna in est adipiscing in phasellus non in justo.",
    "rating": 4.0,
    "code": "Y523201",
    "type": "accessories",
    "brand": "Nike",
    "category": "Clothe",
    "discount": "20% Cashback",
    "quantity": 1,
    "isBestSeller": false
  },
  {
    "id": 7,
    "img": "assets/7.png",
    "name": "Perfume",
    "price": 50.0,
    "oldPrice": 150.0,
    "description": "Lorem ipsum dolor sit amet, consectetur adipiscing elit. Magna in est adipiscing in phasellus non in justo.",
    "rating": 3,
    "code": "Y523201",
    "type": "accessories",
    "brand": "Vke",
    "category": "Perfume",
    "discount": "20% Cashback",
    "quantity": 1,
    "isBestSeller": true
  },
  {
    "id": 8,
    "img": "assets/8.png",
    "name": "Present box",
    "price": 120.0,
    "oldPrice": 150.0,
    "description": "Lorem ipsum dolor sit amet, consectetur adipiscing elit. Magna in est adipiscing in phasellus non in justo.",
    "rating": 5.0,
    "code": "Y523201",
    "type": "accessories",
    "brand": "Glossinness",
    "category": "Jewellery",
    "discount": "5% Cashback Offer",
    "quantity": 1,
    "isBestSeller": false
  },
  {
    "id": 9,
    "img": "assets/CardsImages.png",
    "name": "Bracelet",
    "price": 470.0,
    "oldPrice": 590.0,
    "description": "Lorem ipsum dolor sit amet, consectetur adipiscing elit. Magna in est adipiscing in phasellus non in justo.",
    "rating": 4.0,
    "code": "Y523201",
    "type": "accessories",
    "brand": "Glossinness",
    "category": "Jewellery",
    "discount": "5% Cashback Offer",
    "quantity": 1,
    "isBestSeller": true
  },
  {
    "id": 10,
    "img": "assets/CardsImages1.png",
    "name": "Ring",
    "price": 600.0,
    "oldPrice": 860.0,
    "description": "Lorem ipsum dolor sit amet, consectetur adipiscing elit. Magna in est adipiscing in phasellus non in justo.",
    "rating": 5.0,
    "code": "Y523201",
    "type": "accessories",
    "brand": "Glossinness",
    "category": "Jewellery",
    "discount": "5% Cashback Offer",
    "quantity": 1,
    "isBestSeller": false
  },
  {
    "id": 11,
    "img": "assets/Chair.png",
    "name": "Chair",
    "price": 600.0,
    "oldPrice": 860.0,
    "description": "Lorem ipsum dolor sit amet, consectetur adipiscing elit. Magna in est adipiscing in phasellus non in justo.",
    "rating": 5.0,
    "code": "Y523201",
    "type": "accessories",
    "brand": "Glossinness",
    "category": "Jewellery",
    "discount": "5% Cashback Offer",
    "quantity": 1,
    "isBestSeller": true
  }
]
